{
    "version": 2,
    "builds": [
	{ "src": "package.json", "use": "@now/static-build"},
	{ "src": "./index.js", "use": "@now/node-server" },
	{ "src": "./routes/index.js", "use": "@now/node-server" },
	{ "src": "./app.js", "use": "@now/node-server" },
   { "src": "./routes/*.js", "use": "@now/node-server" }
    ],
    "routes": [
	{ "src": "/", "dest": "./routes/index.js" },
	{ "src": "/checkout", "dest": "/" },
   { "src": "/index-2", "dest": "/" },
   { "src": "/login-register", "dest": "/" },
   { "src": "/shop-left-sidebar", "dest": "/" },
   { "src": "/shopping-carts", "dest": "/" },
   { "src": "/single-product", "dest": "/" }
    ]
}
